otvetmailru/__init__.py
otvetmailru/categories.py
otvetmailru/client.py
otvetmailru/error.py
otvetmailru/factories.py
otvetmailru/models.py
otvetmailru/rates.py
otvetmailru/utils.py
otvetmailru-0.2.2.dist-info/LICENSE
otvetmailru-0.2.2.dist-info/METADATA
otvetmailru-0.2.2.dist-info/WHEEL
otvetmailru-0.2.2.dist-info/top_level.txt
otvetmailru-0.2.2.dist-info/RECORD
