Metadata-Version: 2.1
Name: otvetmailru
Version: 0.2.2
Summary: otvet.mail.ru API wrapper
Home-page: https://github.com/kalinochkind/otvetmailru
Author: Denis Kalinochkin
Author-email: kalinochkind@gmail.com
License: MIT
Keywords: otvet mail.ru
Platform: UNKNOWN
Classifier: Development Status :: 3 - Alpha
Classifier: Intended Audience :: Developers
Classifier: License :: OSI Approved :: MIT License
Classifier: Operating System :: OS Independent
Classifier: Programming Language :: Python :: 3
Classifier: Programming Language :: Python :: 3.6
Classifier: Programming Language :: Python :: 3.7
Classifier: Programming Language :: Python :: 3.8
Classifier: Programming Language :: Python :: 3.9
Requires-Python: >=3.6
Requires-Dist: requests
Requires-Dist: dataclasses ; python_version < "3.7"
